aws_iam_db/__init__.py
aws_iam_db/__main__.py
aws_iam_db/build_db.py
aws_iam_db/docs.py
aws_iam_db-0.0.2.dist-info/LICENSE
aws_iam_db-0.0.2.dist-info/METADATA
aws_iam_db-0.0.2.dist-info/WHEEL
aws_iam_db-0.0.2.dist-info/entry_points.txt
aws_iam_db-0.0.2.dist-info/top_level.txt
aws_iam_db-0.0.2.dist-info/RECORD
