Metadata-Version: 2.1
Name: aws-iam-db
Version: 0.0.2
Summary: Creates a sqlite database of AWS IAM actions
Home-page: https://github.com/zscholl/aws-iam-db
Author: Zak Scholl
Author-email: zak@zakscholl.com
License: UNKNOWN
Project-URL: Bug Tracker, https://github.com/zscholl/aws-iam-db/issues
Platform: UNKNOWN
Classifier: Programming Language :: Python :: 3
Classifier: License :: OSI Approved :: Apache Software License
Classifier: Operating System :: OS Independent
Requires-Python: >=3.6
License-File: LICENSE
Requires-Dist: typer
Requires-Dist: beautifulsoup4
Requires-Dist: sqlalchemy
Requires-Dist: requests
